LICENSE
MANIFEST.in
README.rst
setup.cfg
setup.py
django_lb_adminlte.egg-info/PKG-INFO
django_lb_adminlte.egg-info/SOURCES.txt
django_lb_adminlte.egg-info/dependency_links.txt
django_lb_adminlte.egg-info/requires.txt
django_lb_adminlte.egg-info/top_level.txt
lbadminlte/__init__.py
lbadminlte/tests.py
lbadminlte/static/css/lbadminlte.css
lbadminlte/static/img/favicon.ico
lbadminlte/static/js/django.formset.js
lbadminlte/static/js/lbadminlte.js
lbadminlte/templates/403.html
lbadminlte/templates/404.html
lbadminlte/templates/500.html
lbadminlte/templates/incs/messages.html
lbadminlte/templates/lbadminlte/base.html
lbadminlte/templates/lbadminlte/base_ext.html
lbadminlte/templates/lbadminlte/base_form.html
lbadminlte/templates/lbadminlte/base_formset.html
lbadminlte/templates/lbadminlte/inc_formset.html
lbadminlte/templates/lbadminlte/mbase_popup.html
lbadminlte/templates/lbadminlte/bootstrap3/table_inline_formset.html